antares/study/version/__about__.py
antares/study/version/__init__.py
antares/study/version/__main__.py
antares/study/version/cli.py
antares/study/version/converters.py
antares/study/version/exceptions.py
antares/study/version/ini_reader.py
antares/study/version/ini_writer.py
antares/study/version/py.typed
antares/study/version/__pyinstaller/__init__.py
antares/study/version/__pyinstaller/hook-antares.study.version.py
antares/study/version/create_app/__init__.py
antares/study/version/create_app/resources/__init__.py
antares/study/version/create_app/resources/empty_study_07.00.zip
antares/study/version/create_app/resources/empty_study_07.01.zip
antares/study/version/create_app/resources/empty_study_07.02.zip
antares/study/version/create_app/resources/empty_study_08.00.zip
antares/study/version/create_app/resources/empty_study_08.01.zip
antares/study/version/create_app/resources/empty_study_08.02.zip
antares/study/version/create_app/resources/empty_study_08.03.zip
antares/study/version/create_app/resources/empty_study_08.04.zip
antares/study/version/create_app/resources/empty_study_08.05.zip
antares/study/version/create_app/resources/empty_study_08.06.zip
antares/study/version/create_app/resources/empty_study_08.07.zip
antares/study/version/create_app/resources/empty_study_08.08.zip
antares/study/version/create_app/resources/empty_study_09.00.zip
antares/study/version/create_app/resources/empty_study_09.02.zip
antares/study/version/create_app/resources/empty_study_09.03.zip
antares/study/version/model/__init__.py
antares/study/version/model/exceptions.py
antares/study/version/model/general_data.py
antares/study/version/model/study_antares.py
antares/study/version/model/study_version.py
antares/study/version/show_app/__init__.py
antares/study/version/upgrade_app/__init__.py
antares/study/version/upgrade_app/exceptions.py
antares/study/version/upgrade_app/helpers.py
antares/study/version/upgrade_app/scenario_mapping.py
antares/study/version/upgrade_app/upgrade_method.py
antares_study_version-1.0.20.dist-info/licenses/LICENSE.md
antares_study_version-1.0.20.dist-info/METADATA
antares_study_version-1.0.20.dist-info/WHEEL
antares_study_version-1.0.20.dist-info/entry_points.txt
antares_study_version-1.0.20.dist-info/top_level.txt
antares_study_version-1.0.20.dist-info/RECORD
