Metadata-Version: 2.4
Name: antares-study-version
Version: 1.0.20
Summary: Study version manager for Antares ecosystem
Author-email: Laurent LAPORTE <laurent.laporte.pro@gmail.com>
License: MIT
Project-URL: Documentation, https://github.com/AntaresSimulatorTeam/antares-study-version#readme
Project-URL: Issues, https://github.com/AntaresSimulatorTeam/antares-study-version/issues
Project-URL: Source, https://github.com/AntaresSimulatorTeam/antares-study-version
Keywords: antares,study,config,configuration,model,versionning
Classifier: Development Status :: 4 - Beta
Classifier: Programming Language :: Python
Classifier: Programming Language :: Python :: 3.10
Classifier: Programming Language :: Python :: 3.11
Classifier: Programming Language :: Python :: 3.12
Classifier: Programming Language :: Python :: Implementation :: CPython
Classifier: Programming Language :: Python :: Implementation :: PyPy
Requires-Python: >=3.10
License-File: LICENSE.md
Requires-Dist: click
Requires-Dist: pandas
Dynamic: license-file
